orbeon_xml_api/__init__.py
orbeon_xml_api/builder.py
orbeon_xml_api/controls.py
orbeon_xml_api/runner.py
orbeon_xml_api/runner_copy_builder_merge.py
orbeon_xml_api/utils.py
orbeon_xml_api-0.1.0.dev28.dist-info/LICENSE
orbeon_xml_api-0.1.0.dev28.dist-info/METADATA
orbeon_xml_api-0.1.0.dev28.dist-info/WHEEL
orbeon_xml_api-0.1.0.dev28.dist-info/top_level.txt
orbeon_xml_api-0.1.0.dev28.dist-info/RECORD
