Metadata-Version: 2.1
Name: orbeon-xml-api
Version: 0.1.0.dev28
Summary: A Python object API for Orbeon XML
Home-page: https://github.com/bobslee/orbeon-xml-api
Author: Bob Leers
Author-email: bob@novacode.nl
License: MIT
Platform: UNKNOWN
Requires-Dist: lxml
Requires-Dist: xmltodict
Requires-Dist: xmlunittest
